fiduswriter/website/__init__.py
fiduswriter/website/admin.py
fiduswriter/website/apps.py
fiduswriter/website/emails.py
fiduswriter/website/models.py
fiduswriter/website/urls.py
fiduswriter/website/views.py
fiduswriter/website/migrations/0001_initial.py
fiduswriter/website/migrations/0002_auto_20220703_1201.py
fiduswriter/website/migrations/0003_auto_20220707_1955.py
fiduswriter/website/migrations/0004_publication_title.py
fiduswriter/website/migrations/0005_auto_20220715_1044.py
fiduswriter/website/migrations/0006_auto_20220715_1350.py
fiduswriter/website/migrations/0007_publication_abstract.py
fiduswriter/website/migrations/0008_alter_editor_user.py
fiduswriter/website/migrations/0009_design.py
fiduswriter/website/migrations/0010_alter_publication_status.py
fiduswriter/website/migrations/0011_alter_authors.py
fiduswriter/website/migrations/0012_editor_group.py
fiduswriter/website/migrations/0013_delete_editor.py
fiduswriter/website/migrations/__init__.py
fiduswriter/website/static/css/website.css
fiduswriter/website/static/js/modules/website/app.js
fiduswriter/website/static/js/modules/website/editor.js
fiduswriter/website/static/js/modules/website/index.js
fiduswriter/website/static/js/modules/website/menu.js
fiduswriter/website/static/js/modules/website/publish_doc.js
fiduswriter/website/static/js/modules/website/templates.js
fiduswriter/website/static/js/modules/website/tools.js
fiduswriter/website/static/js/modules/website/website/article.js
fiduswriter/website/static/js/modules/website/website/overview.js
fiduswriter/website/static/js/modules/website/website/templates.js
fiduswriter/website/static/js/plugins/app/website.js
fiduswriter/website/static/js/plugins/editor/website.js
fiduswriter/website/static/js/plugins/menu/website.js
fiduswriter/website/static/js/plugins/website/init.js
fiduswriter/website/tests/__init__.py
fiduswriter/website/tests/test_website.py
fiduswriter_website-4.0.0.dist-info/licenses/LICENSE
fiduswriter_website-4.0.0.dist-info/METADATA
fiduswriter_website-4.0.0.dist-info/WHEEL
fiduswriter_website-4.0.0.dist-info/top_level.txt
fiduswriter_website-4.0.0.dist-info/RECORD
