Metadata-Version: 2.4
Name: fiduswriter-website
Version: 4.0.0
Summary: A Fidus Writer plugin to allow publishing articles publically directly.
Author-email: Johannes Wilm <johannes@fiduswriter.org>
License: AGPL-3.0-or-later
Project-URL: homepage, https://www.fiduswriter.org
Project-URL: repository, https://www.github.com/fiduswriter/fiduswriter-website
Classifier: Development Status :: 5 - Production/Stable
Classifier: Intended Audience :: Science/Research
Classifier: Framework :: Django :: 5.1
Classifier: License :: OSI Approved :: GNU Affero General Public License v3
Classifier: Programming Language :: Python :: 3
Classifier: Topic :: Scientific/Engineering
Classifier: Topic :: Text Editors :: Word Processors
Classifier: Topic :: Text Processing
Classifier: Topic :: Text Processing :: Markup :: HTML
Classifier: Topic :: Utilities
Classifier: Topic :: Internet :: WWW/HTTP :: Dynamic Content
License-File: LICENSE
Requires-Dist: fiduswriter
Dynamic: license-file
